ndict.py
setup.py
ndict.egg-info/PKG-INFO
ndict.egg-info/SOURCES.txt
ndict.egg-info/dependency_links.txt
ndict.egg-info/top_level.txt