Metadata-Version: 1.1
Name: ndict
Version: 0.1
Summary: Named dict for python based on common dict
Home-page: https://github.com/jet9/python-ndict
Author: Dmitry Kurbatov
Author-email: dk@dimcha.ru
License: BSD
Platform: UNKNOWN
Classifier: Development Status :: 4 - Beta
Classifier: Environment :: Console
Classifier: Intended Audience :: Developers
Classifier: License :: OSI Approved :: BSD License
Classifier: Operating System :: OS Independent
Classifier: Programming Language :: Python
